README.md
setup.py
pal/__init__.py
pal/backtracking_line_search.py
paldgp.egg-info/PKG-INFO
paldgp.egg-info/SOURCES.txt
paldgp.egg-info/dependency_links.txt
paldgp.egg-info/requires.txt
paldgp.egg-info/top_level.txt